pymip/__init__.py
pymip/utils.py
pymip/api/__init__.py
pymip/api/analysis.py
pymip/api/archive.py
pymip/api/config.py
pymip/api/genelist.py
pymip/api/pedigree.py
pymip/api/sampleinfo.py
pymip/api/scout.py
pymip/archive/__init__.py
pymip/archive/core.py
pymip/archive/prepare.py
pymip/cli/__init__.py
pymip/cli/archive.py
pymip/cli/base.py
pymip/cli/log.py
pymip/cli/prepare.py
pymip-0.2.0.dist-info/DESCRIPTION.rst
pymip-0.2.0.dist-info/METADATA
pymip-0.2.0.dist-info/RECORD
pymip-0.2.0.dist-info/WHEEL
pymip-0.2.0.dist-info/entry_points.txt
pymip-0.2.0.dist-info/metadata.json
pymip-0.2.0.dist-info/top_level.txt
