Metadata-Version: 2.0
Name: pymip
Version: 0.2.0
Summary: Provides a Python API to manipulate MIP
Home-page: https://github.com/robinandeer/pymip
Author: Robin Andeer
Author-email: robin.andeer@gmail.com
License: MIT
Keywords: p,y,m,i,p, ,d,e,v,e,l,o,p,m,e,n,t
Platform: UNKNOWN
Classifier: Development Status :: 3 - Alpha
Classifier: Intended Audience :: Developers
Classifier: Topic :: Software Development
Classifier: License :: OSI Approved :: MIT License
Classifier: Programming Language :: Python :: 2
Classifier: Programming Language :: Python :: 2.7
Classifier: Programming Language :: Python :: 3
Classifier: Programming Language :: Python :: 3.3
Classifier: Programming Language :: Python :: 3.4
Classifier: Environment :: Console
Requires-Dist: click
Requires-Dist: path.py
Requires-Dist: ped-parser
Requires-Dist: pyyaml
Requires-Dist: setuptools
